pyjsonnet/__init__.py
pyjsonnet/render_jsonnet.py
pyjsonnet/template_filters.py
pyjsonnet/utils.py
pyjsonnet/commands/__init__.py
pyjsonnet/commands/cli.py
pyjsonnet/commands/command_base.py
pyjsonnet/commands/jsonnet.py
pyjsonnet/commands/version.py
pyjsonnet/jsonnet/lib/jpy-utils.libsonnet
pyjsonnet/jsonnet/lib/test_jutils.jsonnet
pyjsonnet/jsonnet/lib/jpy-utils/appr.libsonnet
pyjsonnet/jsonnet/lib/jpy-utils/docker.libsonnet
pyjsonnet/jsonnet/lib/jpy-utils/extended_std.libsonnet
pyjsonnet/jsonnet/lib/jpy-utils/gitlab-ci.libsonnet
pyjsonnet/jsonnet/lib/jpy-utils/helm.libsonnet
pyjsonnet/jsonnet/lib/jpy-utils/k8s.libsonnet
pyjsonnet/jsonnet/lib/jpy-utils/native_extensions.libsonnet
pyjsonnet/jsonnet/lib/jpy-utils/tests_utils.libsonnet
pyjsonnet-0.0.4.data/scripts/pyjsonnet
pyjsonnet-0.0.4.dist-info/DESCRIPTION.rst
pyjsonnet-0.0.4.dist-info/METADATA
pyjsonnet-0.0.4.dist-info/RECORD
pyjsonnet-0.0.4.dist-info/WHEEL
pyjsonnet-0.0.4.dist-info/metadata.json
pyjsonnet-0.0.4.dist-info/top_level.txt
