Metadata-Version: 2.0
Name: pyjsonnet
Version: 0.0.4
Summary: pyjsonnet
Home-page: https://github.com/ant31/pyjsonnet
Author: Antoine Legrand
Author-email: 2t.antoine@gmail.com
License: Apache License version 2
Keywords: pyjsonnet
Platform: UNKNOWN
Classifier: Development Status :: 2 - Pre-Alpha
Classifier: Intended Audience :: Developers
Classifier: Natural Language :: English
Classifier: Programming Language :: Python :: 2
Classifier: Programming Language :: Python :: 2.7
Requires-Dist: futures
Requires-Dist: pyyaml
Requires-Dist: jsonnet
Requires-Dist: jinja2 (>=2.8)
